japan_dem-0.1.1.dist-info/METADATA
japan_dem-0.1.1.dist-info/WHEEL
japan_dem/__init__.py
japan_dem/japan_dem.abi3.so
japan_dem-0.1.1.dist-info/RECORD
