Metadata-Version: 2.4
Name: japan-dem
Version: 0.1.1
Classifier: Programming Language :: Rust
Classifier: Programming Language :: Python :: Implementation :: CPython
Classifier: Programming Language :: Python :: Implementation :: PyPy
Classifier: Programming Language :: Python :: 3.9
Classifier: Programming Language :: Python :: 3.10
Classifier: Programming Language :: Python :: 3.11
Classifier: Programming Language :: Python :: 3.12
Summary: Python bindings for japan DEM XML parser
Keywords: gis,dem,geotiff,japan,gsi
Author: nokonoko1203 <email@example.com>
Author-email: nokonoko1203 <email@example.com>
License: MIT
Requires-Python: >=3.9
Project-URL: Source Code, https://github.com/nokonoko1203/japan-dem
